setup.py
src/TravelingSalesman/TSM_class.py
src/TravelingSalesman/__about__.py
src/TravelingSalesman/__init__.py
tsmtest-0.0.1.dist-info/METADATA
tsmtest-0.0.1.dist-info/WHEEL
tsmtest-0.0.1.dist-info/licenses/LICENSE
tsmtest-0.0.1.dist-info/RECORD
