Metadata-Version: 2.1
Name: TSMtest
Version: 0.0.1
Summary: Traveling salesman problem for testing and benchmarking optimization algorithms
Project-URL: Homepage, https://github.com/Tommer-R/Traveling-salesman
Project-URL: Bug Tracker, https://github.com/Tommer-R/Traveling-salesman/issues
Author-email: Tommer Rissin <tommerrissin@gmail.com>
License: MIT License
License-File: LICENSE
Classifier: License :: OSI Approved :: MIT License
Classifier: Operating System :: OS Independent
Classifier: Programming Language :: Python :: 3
Requires-Python: >=3.7
